Outliers_final/__init__.py
Outliers_final/outliers.py
Outliers_final-1.0.3.dist-info/LICENSE.txt
Outliers_final-1.0.3.dist-info/METADATA
Outliers_final-1.0.3.dist-info/WHEEL
Outliers_final-1.0.3.dist-info/entry_points.txt
Outliers_final-1.0.3.dist-info/top_level.txt
Outliers_final-1.0.3.dist-info/RECORD
