Metadata-Version: 2.1
Name: Outliers-final
Version: 1.0.3
Summary: outliers removal using quantiles
Home-page: UNKNOWN
Author: Rohan Bawa
License: MIT
Keywords: outliers removal
Platform: UNKNOWN
Classifier: Development Status :: 3 - Alpha
Classifier: Intended Audience :: Developers
Classifier: Topic :: Software Development :: Build Tools
Classifier: License :: OSI Approved :: MIT License
Classifier: Programming Language :: Python :: 3
Classifier: Programming Language :: Python :: 3.4
Classifier: Programming Language :: Python :: 3.5
Classifier: Programming Language :: Python :: 3.6
Classifier: Programming Language :: Python :: 3.6
Requires-Dist: numpy
